[{"id":"science-medical","thumb":"icon ion-beaker","name":"Medical Science","desc":"Try curing this!"},{"id":"science-biology","thumb":"icon ion-beaker","name":"Biology","desc":"The science of living things"},{"id":"science-astronomy","thumb":"icon ion-beaker","name":"Astronomy","desc":"How many stars can you get here?"},{"id":"science-forensic","thumb":"icon ion-beaker","name":"Forensic Science","desc":"For every case"},{"id":"science-chemistry","thumb":"icon ion-beaker","name":"Chemistry","desc":"Life is a chemical cocktail"},{"id":"science-cs","thumb":"icon ion-beaker","name":"Computer Science","desc":"Computing is always fun"},{"id":"science-physics","thumb":"icon ion-beaker","name":"Physics","desc":"For every action there is ..."}]